{"cameraMode":{"drawMode":0,"name":"Shaded","section":"Shading Mode"},"sceneLighting":true,"audioPlay":false,"sceneViewState":{"showFog":true,"showMaterialUpdate":false,"showSkybox":true,"showFlares":true,"showImageEffects":true,"showParticleSystems":true},"in2DMode":false,"pivot":{"x":-0.12376316636800766,"y":0.8331557512283325,"z":0.33670157194137576},"rotation":{"x":-0.036800578236579898,"y":0.06948880851268769,"z":-0.002565574599429965,"w":-0.9969050884246826},"size":2.642760992050171,"orthographic":false}